modulename_inz/__init__.py
modulename_inz/__main__.py
modulename_inz/names.txt
modulename_inz/speaker.py
modulename_inz/speakers/Inzamam.py
modulename_inz/speakers/__init__.py
modulename_inz-0.3.0.dist-info/licenses/LICENSE.txt
modulename_inz-0.3.0.dist-info/METADATA
modulename_inz-0.3.0.dist-info/WHEEL
modulename_inz-0.3.0.dist-info/entry_points.txt
modulename_inz-0.3.0.dist-info/top_level.txt
modulename_inz-0.3.0.dist-info/RECORD
