Metadata-Version: 2.4
Name: modulename_inz
Version: 0.3.0
Summary: My first package!
Author-email: Inzamam <inzamamshajahan@gmail.com>
Maintainer-email: Inzamam <inzamamshajahan@gmail.com>
License: Copyright 2025 Muhammed Inzamam
Project-URL: Homepage, https://github.com/inzamamshajahan
Project-URL: Documentation, https://github.com/inzamamshajahan
Keywords: Furuness
Classifier: Programming Language :: Python :: 3.9
Classifier: Programming Language :: Python :: Implementation :: CPython
Classifier: License :: OSI Approved :: BSD License
Classifier: Intended Audience :: Developers
Classifier: Operating System :: POSIX :: Linux
Classifier: Operating System :: Microsoft :: Windows
Classifier: Operating System :: MacOS
Classifier: Operating System :: MacOS :: MacOS X
Requires-Python: >=3.9
License-File: LICENSE.txt
Requires-Dist: colorama~=0.0
Provides-Extra: dev
Requires-Dist: twine; extra == "dev"
Requires-Dist: build; extra == "dev"
Dynamic: license-file
